{
  "event": "2017",
  "members": {
    "116481": {
      "completion_day_level": {},
      "global_score": 0,
      "id": "116481",
      "last_star_ts": "1969-12-31T19:00:00-0500",
      "local_score": 0,
      "name": "mozesmagyar",
      "stars": 0
    },
    "117917": {
      "completion_day_level": {},
      "global_score": 0,
      "id": "117917",
      "last_star_ts": "1969-12-31T19:00:00-0500",
      "local_score": 0,
      "name": "adambysice",
      "stars": 0
    },
    "118311": {
      "completion_day_level": {
        "1": {
          "1": {
            "get_star_ts": "2017-12-02T23:52:07-0500"
          },
          "2": {
            "get_star_ts": "2017-12-03T00:14:30-0500"
          }
        },
        "2": {
          "1": {
            "get_star_ts": "2017-12-03T00:30:28-0500"
          },
          "2": {
            "get_star_ts": "2017-12-03T01:04:28-0500"
          }
        },
        "3": {
          "1": {
            "get_star_ts": "2017-12-03T15:05:34-0500"
          },
          "2": {
            "get_star_ts": "2017-12-03T19:52:08-0500"
          }
        },
        "4": {
          "1": {
            "get_star_ts": "2017-12-04T00:04:02-0500"
          },
          "2": {
            "get_star_ts": "2017-12-04T00:15:04-0500"
          }
        }
      },
      "global_score": 0,
      "id": "118311",
      "last_star_ts": "2017-12-04T00:15:04-0500",
      "local_score": 97,
      "name": "Noah Kipin",
      "stars": 8
    },
    "118403": {
      "completion_day_level": {
        "1": {
          "1": {
            "get_star_ts": "2017-12-01T10:32:19-0500"
          },
          "2": {
            "get_star_ts": "2017-12-01T10:36:42-0500"
          }
        },
        "2": {
          "1": {
            "get_star_ts": "2017-12-06T09:17:35-0500"
          },
          "2": {
            "get_star_ts": "2017-12-06T09:23:37-0500"
          }
        },
        "3": {
          "1": {
            "get_star_ts": "2017-12-06T09:47:08-0500"
          },
          "2": {
            "get_star_ts": "2017-12-06T10:05:47-0500"
          }
        },
        "4": {
          "1": {
            "get_star_ts": "2017-12-06T10:32:38-0500"
          },
          "2": {
            "get_star_ts": "2017-12-06T10:34:38-0500"
          }
        },
        "5": {
          "1": {
            "get_star_ts": "2017-12-06T10:53:35-0500"
          },
          "2": {
            "get_star_ts": "2017-12-06T10:55:04-0500"
          }
        },
        "6": {
          "1": {
            "get_star_ts": "2017-12-06T12:28:23-0500"
          },
          "2": {
            "get_star_ts": "2017-12-06T12:28:43-0500"
          }
        }
      },
      "global_score": 0,
      "id": "118403",
      "last_star_ts": "2017-12-06T12:28:43-0500",
      "local_score": 120,
      "name": "Peter Chau",
      "stars": 12
    },
    "118426": {
      "completion_day_level": {
        "1": {
          "1": {
            "get_star_ts": "2017-12-01T10:58:14-0500"
          },
          "2": {
            "get_star_ts": "2017-12-01T11:13:19-0500"
          }
        },
        "2": {
          "1": {
            "get_star_ts": "2017-12-04T14:45:32-0500"
          },
          "2": {
            "get_star_ts": "2017-12-04T14:50:51-0500"
          }
        },
        "3": {
          "1": {
            "get_star_ts": "2017-12-04T18:44:44-0500"
          },
          "2": {
            "get_star_ts": "2017-12-05T14:06:14-0500"
          }
        },
        "4": {
          "1": {
            "get_star_ts": "2017-12-05T14:14:23-0500"
          },
          "2": {
            "get_star_ts": "2017-12-05T14:22:55-0500"
          }
        },
        "5": {
          "1": {
            "get_star_ts": "2017-12-05T14:58:56-0500"
          },
          "2": {
            "get_star_ts": "2017-12-05T15:03:25-0500"
          }
        },
        "6": {
          "1": {
            "get_star_ts": "2017-12-06T00:23:28-0500"
          },
          "2": {
            "get_star_ts": "2017-12-06T00:35:31-0500"
          }
        },
        "7": {
          "1": {
            "get_star_ts": "2017-12-07T00:08:25-0500"
          }
        }
      },
      "global_score": 0,
      "id": "118426",
      "last_star_ts": "2017-12-07T00:08:25-0500",
      "local_score": 161,
      "name": "James Bannerman",
      "stars": 13
    },
    "118609": {
      "completion_day_level": {
        "1": {
          "1": {
            "get_star_ts": "2017-12-01T00:05:24-0500"
          },
          "2": {
            "get_star_ts": "2017-12-01T00:06:02-0500"
          }
        },
        "2": {
          "1": {
            "get_star_ts": "2017-12-02T00:03:28-0500"
          },
          "2": {
            "get_star_ts": "2017-12-02T00:07:23-0500"
          }
        },
        "3": {
          "1": {
            "get_star_ts": "2017-12-03T00:12:04-0500"
          },
          "2": {
            "get_star_ts": "2017-12-03T00:43:30-0500"
          }
        },
        "4": {
          "1": {
            "get_star_ts": "2017-12-04T00:02:26-0500"
          },
          "2": {
            "get_star_ts": "2017-12-04T00:05:24-0500"
          }
        },
        "5": {
          "1": {
            "get_star_ts": "2017-12-05T00:04:53-0500"
          },
          "2": {
            "get_star_ts": "2017-12-05T00:05:39-0500"
          }
        },
        "6": {
          "1": {
            "get_star_ts": "2017-12-06T00:26:42-0500"
          },
          "2": {
            "get_star_ts": "2017-12-06T00:27:23-0500"
          }
        },
        "7": {
          "1": {
            "get_star_ts": "2017-12-07T00:13:11-0500"
          }
        }
      },
      "global_score": 6,
      "id": "118609",
      "last_star_ts": "2017-12-07T00:13:11-0500",
      "local_score": 260,
      "name": "Michael Tardibuono",
      "stars": 13
    },
    "118852": {
      "completion_day_level": {},
      "global_score": 0,
      "id": "118852",
      "last_star_ts": "1969-12-31T19:00:00-0500",
      "local_score": 0,
      "name": "Michel ElNacouzi",
      "stars": 0
    },
    "119856": {
      "completion_day_level": {},
      "global_score": 0,
      "id": "119856",
      "last_star_ts": "1969-12-31T19:00:00-0500",
      "local_score": 0,
      "name": "imnottommy",
      "stars": 0
    },
    "120850": {
      "completion_day_level": {},
      "global_score": 0,
      "id": "120850",
      "last_star_ts": "1969-12-31T19:00:00-0500",
      "local_score": 0,
      "name": "Sannie Loi",
      "stars": 0
    },
    "122937": {
      "completion_day_level": {},
      "global_score": 0,
      "id": "122937",
      "last_star_ts": "1969-12-31T19:00:00-0500",
      "local_score": 0,
      "name": "iamjackg",
      "stars": 0
    },
    "123142": {
      "completion_day_level": {
        "1": {
          "1": {
            "get_star_ts": "2017-12-01T00:08:45-0500"
          },
          "2": {
            "get_star_ts": "2017-12-01T00:10:04-0500"
          }
        },
        "2": {
          "1": {
            "get_star_ts": "2017-12-02T00:05:11-0500"
          },
          "2": {
            "get_star_ts": "2017-12-02T00:10:18-0500"
          }
        },
        "3": {
          "1": {
            "get_star_ts": "2017-12-03T12:29:56-0500"
          },
          "2": {
            "get_star_ts": "2017-12-03T13:42:51-0500"
          }
        },
        "4": {
          "1": {
            "get_star_ts": "2017-12-04T00:03:52-0500"
          },
          "2": {
            "get_star_ts": "2017-12-04T00:05:41-0500"
          }
        },
        "5": {
          "1": {
            "get_star_ts": "2017-12-05T00:12:12-0500"
          },
          "2": {
            "get_star_ts": "2017-12-05T00:13:43-0500"
          }
        },
        "6": {
          "1": {
            "get_star_ts": "2017-12-06T00:22:05-0500"
          },
          "2": {
            "get_star_ts": "2017-12-06T00:23:33-0500"
          }
        },
        "7": {
          "1": {
            "get_star_ts": "2017-12-07T00:17:15-0500"
          }
        }
      },
      "global_score": 0,
      "id": "123142",
      "last_star_ts": "2017-12-07T00:17:15-0500",
      "local_score": 226,
      "name": "pingpongkingkong",
      "stars": 13
    },
    "137785": {
      "completion_day_level": {
        "1": {
          "1": {
            "get_star_ts": "2017-12-01T00:05:13-0500"
          },
          "2": {
            "get_star_ts": "2017-12-01T00:17:42-0500"
          }
        },
        "2": {
          "1": {
            "get_star_ts": "2017-12-02T00:04:03-0500"
          },
          "2": {
            "get_star_ts": "2017-12-02T00:13:40-0500"
          }
        },
        "3": {
          "1": {
            "get_star_ts": "2017-12-03T00:09:41-0500"
          },
          "2": {
            "get_star_ts": "2017-12-03T00:34:30-0500"
          }
        },
        "4": {
          "1": {
            "get_star_ts": "2017-12-04T00:04:39-0500"
          },
          "2": {
            "get_star_ts": "2017-12-04T00:06:33-0500"
          }
        },
        "5": {
          "1": {
            "get_star_ts": "2017-12-05T00:07:18-0500"
          },
          "2": {
            "get_star_ts": "2017-12-05T00:22:02-0500"
          }
        },
        "6": {
          "1": {
            "get_star_ts": "2017-12-06T00:12:27-0500"
          },
          "2": {
            "get_star_ts": "2017-12-06T00:15:08-0500"
          }
        },
        "7": {
          "1": {
            "get_star_ts": "2017-12-07T00:21:43-0500"
          }
        }
      },
      "global_score": 0,
      "id": "137785",
      "last_star_ts": "2017-12-07T00:21:43-0500",
      "local_score": 244,
      "name": "vincentr21",
      "stars": 13
    },
    "155047": {
      "completion_day_level": {
        "1": {
          "1": {
            "get_star_ts": "2017-12-01T11:13:20-0500"
          },
          "2": {
            "get_star_ts": "2017-12-01T11:27:08-0500"
          }
        },
        "2": {
          "1": {
            "get_star_ts": "2017-12-02T12:07:45-0500"
          },
          "2": {
            "get_star_ts": "2017-12-02T12:23:59-0500"
          }
        },
        "3": {
          "1": {
            "get_star_ts": "2017-12-03T01:33:13-0500"
          },
          "2": {
            "get_star_ts": "2017-12-03T01:57:32-0500"
          }
        },
        "4": {
          "1": {
            "get_star_ts": "2017-12-04T00:31:11-0500"
          },
          "2": {
            "get_star_ts": "2017-12-04T00:42:59-0500"
          }
        },
        "5": {
          "1": {
            "get_star_ts": "2017-12-05T00:28:25-0500"
          },
          "2": {
            "get_star_ts": "2017-12-05T00:33:07-0500"
          }
        },
        "6": {
          "1": {
            "get_star_ts": "2017-12-06T00:50:11-0500"
          },
          "2": {
            "get_star_ts": "2017-12-06T00:54:10-0500"
          }
        }
      },
      "global_score": 0,
      "id": "155047",
      "last_star_ts": "2017-12-06T00:54:10-0500",
      "local_score": 161,
      "name": "Ivan Peng",
      "stars": 12
    },
    "170332": {
      "completion_day_level": {},
      "global_score": 0,
      "id": "170332",
      "last_star_ts": "1969-12-31T19:00:00-0500",
      "local_score": 0,
      "name": null,
      "stars": 0
    },
    "186091": {
      "completion_day_level": {
        "1": {
          "1": {
            "get_star_ts": "2017-12-01T10:45:01-0500"
          },
          "2": {
            "get_star_ts": "2017-12-01T11:08:14-0500"
          }
        },
        "2": {
          "1": {
            "get_star_ts": "2017-12-02T00:16:56-0500"
          },
          "2": {
            "get_star_ts": "2017-12-02T00:37:16-0500"
          }
        },
        "3": {
          "1": {
            "get_star_ts": "2017-12-04T23:07:05-0500"
          },
          "2": {
            "get_star_ts": "2017-12-05T00:11:08-0500"
          }
        },
        "4": {
          "1": {
            "get_star_ts": "2017-12-05T10:42:03-0500"
          },
          "2": {
            "get_star_ts": "2017-12-05T10:46:07-0500"
          }
        },
        "5": {
          "1": {
            "get_star_ts": "2017-12-05T17:28:26-0500"
          },
          "2": {
            "get_star_ts": "2017-12-05T17:35:19-0500"
          }
        },
        "6": {
          "1": {
            "get_star_ts": "2017-12-06T10:07:47-0500"
          },
          "2": {
            "get_star_ts": "2017-12-06T10:12:43-0500"
          }
        }
      },
      "global_score": 0,
      "id": "186091",
      "last_star_ts": "2017-12-06T10:12:43-0500",
      "local_score": 139,
      "name": "Adam Harvie",
      "stars": 12
    },
    "186094": {
      "completion_day_level": {
        "1": {
          "1": {
            "get_star_ts": "2017-12-01T00:13:11-0500"
          },
          "2": {
            "get_star_ts": "2017-12-01T00:19:42-0500"
          }
        },
        "2": {
          "1": {
            "get_star_ts": "2017-12-02T00:06:43-0500"
          },
          "2": {
            "get_star_ts": "2017-12-02T00:13:40-0500"
          }
        },
        "3": {
          "1": {
            "get_star_ts": "2017-12-03T01:24:31-0500"
          },
          "2": {
            "get_star_ts": "2017-12-03T17:25:46-0500"
          }
        },
        "4": {
          "1": {
            "get_star_ts": "2017-12-04T00:03:23-0500"
          },
          "2": {
            "get_star_ts": "2017-12-04T00:11:00-0500"
          }
        },
        "5": {
          "1": {
            "get_star_ts": "2017-12-05T00:11:41-0500"
          },
          "2": {
            "get_star_ts": "2017-12-05T00:15:33-0500"
          }
        },
        "6": {
          "1": {
            "get_star_ts": "2017-12-06T00:15:34-0500"
          },
          "2": {
            "get_star_ts": "2017-12-06T00:30:19-0500"
          }
        },
        "7": {
          "1": {
            "get_star_ts": "2017-12-07T00:11:09-0500"
          }
        }
      },
      "global_score": 0,
      "id": "186094",
      "last_star_ts": "2017-12-07T00:11:09-0500",
      "local_score": 221,
      "name": "Ricky Kwan",
      "stars": 13
    },
    "195610": {
      "completion_day_level": {
        "1": {
          "1": {
            "get_star_ts": "2017-12-01T00:26:53-0500"
          },
          "2": {
            "get_star_ts": "2017-12-01T00:35:38-0500"
          }
        },
        "2": {
          "1": {
            "get_star_ts": "2017-12-02T00:09:57-0500"
          },
          "2": {
            "get_star_ts": "2017-12-02T00:17:37-0500"
          }
        },
        "3": {
          "1": {
            "get_star_ts": "2017-12-03T00:30:09-0500"
          },
          "2": {
            "get_star_ts": "2017-12-03T01:03:20-0500"
          }
        },
        "4": {
          "1": {
            "get_star_ts": "2017-12-04T22:08:34-0500"
          },
          "2": {
            "get_star_ts": "2017-12-04T23:33:32-0500"
          }
        },
        "5": {
          "1": {
            "get_star_ts": "2017-12-05T00:23:19-0500"
          },
          "2": {
            "get_star_ts": "2017-12-05T00:28:27-0500"
          }
        },
        "6": {
          "1": {
            "get_star_ts": "2017-12-06T00:46:25-0500"
          },
          "2": {
            "get_star_ts": "2017-12-06T00:52:35-0500"
          }
        }
      },
      "global_score": 0,
      "id": "195610",
      "last_star_ts": "2017-12-06T00:52:35-0500",
      "local_score": 180,
      "name": "eolalde",
      "stars": 12
    },
    "195611": {
      "completion_day_level": {
        "1": {
          "1": {
            "get_star_ts": "2017-12-06T10:24:11-0500"
          },
          "2": {
            "get_star_ts": "2017-12-06T10:27:11-0500"
          }
        },
        "2": {
          "1": {
            "get_star_ts": "2017-12-06T12:27:18-0500"
          },
          "2": {
            "get_star_ts": "2017-12-06T12:34:07-0500"
          }
        },
        "3": {
          "1": {
            "get_star_ts": "2017-12-06T14:43:31-0500"
          }
        }
      },
      "global_score": 0,
      "id": "195611",
      "last_star_ts": "2017-12-06T14:43:31-0500",
      "local_score": 40,
      "name": "Dumtard",
      "stars": 5
    },
    "195615": {
      "completion_day_level": {
        "1": {
          "1": {
            "get_star_ts": "2017-12-01T08:52:39-0500"
          },
          "2": {
            "get_star_ts": "2017-12-01T09:05:48-0500"
          }
        },
        "2": {
          "1": {
            "get_star_ts": "2017-12-02T12:12:57-0500"
          },
          "2": {
            "get_star_ts": "2017-12-02T12:22:44-0500"
          }
        },
        "3": {
          "1": {
            "get_star_ts": "2017-12-03T08:58:06-0500"
          },
          "2": {
            "get_star_ts": "2017-12-03T09:56:13-0500"
          }
        },
        "4": {
          "1": {
            "get_star_ts": "2017-12-04T11:12:36-0500"
          },
          "2": {
            "get_star_ts": "2017-12-04T11:20:19-0500"
          }
        },
        "5": {
          "1": {
            "get_star_ts": "2017-12-05T07:29:25-0500"
          },
          "2": {
            "get_star_ts": "2017-12-05T07:32:57-0500"
          }
        },
        "6": {
          "1": {
            "get_star_ts": "2017-12-06T09:35:37-0500"
          },
          "2": {
            "get_star_ts": "2017-12-06T09:45:18-0500"
          }
        }
      },
      "global_score": 0,
      "id": "195615",
      "last_star_ts": "2017-12-06T09:45:18-0500",
      "local_score": 158,
      "name": "danielshanker",
      "stars": 12
    },
    "196695": {
      "completion_day_level": {
        "1": {
          "1": {
            "get_star_ts": "2017-12-01T00:05:46-0500"
          },
          "2": {
            "get_star_ts": "2017-12-01T00:08:58-0500"
          }
        },
        "2": {
          "1": {
            "get_star_ts": "2017-12-02T00:04:58-0500"
          },
          "2": {
            "get_star_ts": "2017-12-02T00:10:10-0500"
          }
        },
        "3": {
          "1": {
            "get_star_ts": "2017-12-03T00:18:30-0500"
          },
          "2": {
            "get_star_ts": "2017-12-03T00:38:01-0500"
          }
        },
        "4": {
          "1": {
            "get_star_ts": "2017-12-04T00:07:10-0500"
          },
          "2": {
            "get_star_ts": "2017-12-04T00:12:32-0500"
          }
        },
        "5": {
          "1": {
            "get_star_ts": "2017-12-05T00:03:08-0500"
          },
          "2": {
            "get_star_ts": "2017-12-05T00:04:18-0500"
          }
        },
        "6": {
          "1": {
            "get_star_ts": "2017-12-06T00:55:38-0500"
          },
          "2": {
            "get_star_ts": "2017-12-06T01:00:58-0500"
          }
        },
        "7": {
          "1": {
            "get_star_ts": "2017-12-07T00:13:14-0500"
          }
        }
      },
      "global_score": 54,
      "id": "196695",
      "last_star_ts": "2017-12-07T00:13:14-0500",
      "local_score": 234,
      "name": "Andrew Walker",
      "stars": 13
    },
    "197423": {
      "completion_day_level": {
        "1": {
          "1": {
            "get_star_ts": "2017-12-01T00:04:55-0500"
          },
          "2": {
            "get_star_ts": "2017-12-01T00:07:04-0500"
          }
        },
        "2": {
          "1": {
            "get_star_ts": "2017-12-02T00:02:30-0500"
          },
          "2": {
            "get_star_ts": "2017-12-02T00:08:03-0500"
          }
        },
        "3": {
          "1": {
            "get_star_ts": "2017-12-03T00:09:31-0500"
          },
          "2": {
            "get_star_ts": "2017-12-03T00:20:08-0500"
          }
        },
        "4": {
          "1": {
            "get_star_ts": "2017-12-04T00:04:03-0500"
          },
          "2": {
            "get_star_ts": "2017-12-04T00:07:57-0500"
          }
        },
        "5": {
          "1": {
            "get_star_ts": "2017-12-05T00:09:39-0500"
          },
          "2": {
            "get_star_ts": "2017-12-05T00:12:03-0500"
          }
        },
        "6": {
          "1": {
            "get_star_ts": "2017-12-06T00:12:06-0500"
          },
          "2": {
            "get_star_ts": "2017-12-06T00:20:30-0500"
          }
        },
        "7": {
          "1": {
            "get_star_ts": "2017-12-07T00:10:08-0500"
          },
          "2": {
            "get_star_ts": "2017-12-07T00:28:39-0500"
          }
        }
      },
      "global_score": 32,
      "id": "197423",
      "last_star_ts": "2017-12-07T00:28:39-0500",
      "local_score": 288,
      "name": null,
      "stars": 14
    },
    "30841": {
      "completion_day_level": {
        "1": {
          "1": {
            "get_star_ts": "2017-12-01T00:11:51-0500"
          },
          "2": {
            "get_star_ts": "2017-12-01T00:15:03-0500"
          }
        },
        "2": {
          "1": {
            "get_star_ts": "2017-12-02T00:03:22-0500"
          },
          "2": {
            "get_star_ts": "2017-12-02T00:08:05-0500"
          }
        },
        "3": {
          "1": {
            "get_star_ts": "2017-12-03T00:48:59-0500"
          },
          "2": {
            "get_star_ts": "2017-12-03T01:57:52-0500"
          }
        },
        "4": {
          "1": {
            "get_star_ts": "2017-12-04T00:02:19-0500"
          },
          "2": {
            "get_star_ts": "2017-12-04T00:12:48-0500"
          }
        },
        "5": {
          "1": {
            "get_star_ts": "2017-12-05T00:05:24-0500"
          },
          "2": {
            "get_star_ts": "2017-12-05T00:06:56-0500"
          }
        },
        "6": {
          "1": {
            "get_star_ts": "2017-12-06T00:13:51-0500"
          },
          "2": {
            "get_star_ts": "2017-12-06T00:21:04-0500"
          }
        },
        "7": {
          "1": {
            "get_star_ts": "2017-12-07T00:06:29-0500"
          }
        }
      },
      "global_score": 0,
      "id": "30841",
      "last_star_ts": "2017-12-07T00:06:29-0500",
      "local_score": 249,
      "name": "bewuethr",
      "stars": 13
    }
  },
  "owner_id": "30841"
}
